loss_mob/__init__.py
loss_mob/loss_mob.py
loss_mob-0.1.17.dist-info/LICENSE.txt
loss_mob-0.1.17.dist-info/METADATA
loss_mob-0.1.17.dist-info/WHEEL
loss_mob-0.1.17.dist-info/top_level.txt
loss_mob-0.1.17.dist-info/RECORD
