Metadata-Version: 2.1
Name: loss_mob
Version: 0.1.17
Summary: Monotonic Optimal Binning for Loss Models
Home-page: https://github.com/statcompute/loss_mob
Author: WenSui Liu
Author-email: liuwensui@gmail.com
Classifier: Programming Language :: Python :: 3
Classifier: License :: OSI Approved :: MIT License
Classifier: Operating System :: OS Independent
License-File: LICENSE.txt
Requires-Dist: numpy
Requires-Dist: scipy
Requires-Dist: scikit-learn
Requires-Dist: tabulate
Requires-Dist: cytoolz
Requires-Dist: dcor
